panda_common-0.0.36.data/data/etc/panda/panda_common.cfg.rpmnew
panda_common-0.0.36.data/scripts/panda_common-install_igtf_ca
pandacommon/__init__.py
pandacommon/liveconfigparser/LiveConfigParser.py
pandacommon/liveconfigparser/__init__.py
pandacommon/pandalogger/LogWrapper.py
pandacommon/pandalogger/PandaLogger.py
pandacommon/pandalogger/__init__.py
pandacommon/pandalogger/logger_config.py
pandacommon/pandalogger/logger_utils.py
pandacommon/pandamsgbkr/__init__.py
pandacommon/pandamsgbkr/msg_bkr_utils.py
pandacommon/pandamsgbkr/msg_processor.py
pandacommon/pandautils/ConfigUtils.py
pandacommon/pandautils/PandaUtils.py
pandacommon/pandautils/__init__.py
pandacommon/pandautils/net_utils.py
pandacommon/pandautils/plugin_factory.py
pandacommon/pandautils/thread_utils.py
pandacommon/pandautils/utils_config.py
pandacommon/test/__init__.py
pandacommon/test/logtest.py
pandacommon/test/mb_test.py
panda_common-0.0.36.dist-info/LICENSE
panda_common-0.0.36.dist-info/METADATA
panda_common-0.0.36.dist-info/WHEEL
panda_common-0.0.36.dist-info/top_level.txt
panda_common-0.0.36.dist-info/RECORD
