Metadata-Version: 2.1
Name: panda-common
Version: 0.0.36
Summary: PanDA Common Package
Home-page: https://twiki.cern.ch/twiki/bin/view/Atlas/PanDA
Author: Panda Team
Author-email: atlas-adc-panda@cern.ch
License: GPL
License-File: LICENSE
Requires-Dist: configparser
Requires-Dist: pytz
Requires-Dist: stomp.py (<=7.0.0,>=4.1.23)
Requires-Dist: requests
